<syntax name="postgres">
	<keywords>
		<word>ABORT</word>
		<word>AGGREGATE</word>
		<word>ANALYZE</word>
		<word>ALIAS</word>
		<word>ALTER</word>
		<word>AND</word>
		<word>AS</word>
		<word>BEGIN</word>
		<word>BETWEEN</word>
		<word>BY</word>
		<word>CHECKPOINT</word>
		<word>CASE</word>
		<word>CAST</word>
		<word>CLASS</word>
		<word>CLOSE</word>
		<word>CLUSTER</word>
		<word>COMMENT</word>
		<word>COMMIT</word>
		<word>CONVERSION</word>
		<word>COPY</word>
		<word>CREATE</word>
		<word>DATABASE</word>
		<word>DEALLOCATE</word>
		<word>DECLARE</word>
		<word>DELETE</word>
		<word>DISTINCT</word>
		<word>DOMAIN</word>
		<word>DROP</word>
		<word>ELSE</word>
		<word>END</word>
		<word>EXECUTE</word>
		<word>EXPLAIN</word>
		<word>FALSE</word>
		<word>FOR</word>
		<word>FROM</word>
		<word>FUNCTION</word>
		<word>GRANT</word>
		<word>GROUP</word>
		<word>IF</word>
		<word>INDEX</word>
		<word>INSERT</word>
		<word>INTO</word>
		<word>IS</word>
		<word>ISNULL</word>
		<word>LANGUAGE</word>
		<word>LIKE</word>
		<word>LOCK</word>
		<word>MOVE</word>
		<word>NOT</word>
		<word>NOTNULL</word>
		<word>NULL</word>
		<word>OPEN</word>
		<word>OPERATOR</word>
		<word>OR</word>
		<word>ORDER</word>
		<word>RETURN</word>
		<word>RETURNS</word>
		<word>RESET</word>
		<word>REVOKE</word>
		<word>ROLE</word>
		<word>ROLLBACK</word>
		<word>RULE</word>
		<word>SAVEPOINT</word>
		<word>SCHEMA</word>
		<word>SELECT</word>
		<word>SEQUENCE</word>
		<word>SET</word>
		<word>SIMILAR</word>
		<word>START</word>
		<word>TABLE</word>
		<word>TABLESPACE</word>
		<word>THEN</word>
		<word>TO</word>
		<word>TRANSACTION</word>
		<word>TRIGGER</word>
		<word>TRUE</word>
		<word>TRUNCATE</word>
		<word>TYPE</word>
		<word>UPDATE</word>
		<word>USER</word>
		<word>VALUES</word>
		<word>VIEW</word>
		<word>WHERE</word>
	</keywords>
	
	<functions>
		<!-- Math functions-->
		<word>ABS</word>
		<word>CEIL</word>
		<word>CEILING</word>
		<word>DEGREES</word>
		<word>EXP</word>
		<word>FLOOR</word>
		<word>LN</word>
		<word>LOG</word>
		<word>MOD</word>
		<word>PI</word>
		<word>POWER</word>
		<word>RADIANS</word>
		<word>RANDOM</word>
		<word>ROUND</word>
		<word>SIGN</word>
		<word>SQRT</word>
		<word>TRUNC</word>
		<!-- Trigonometric functions-->
		<word>ACOS</word>
		<word>ASIN</word>
		<word>ATAN</word>
		<word>ATAN2</word>
		<word>COS</word>
		<word>COT</word>
		<word>SIN</word>
		<word>TAN</word>
		<!-- String functions-->
		<word>BIT_LENGTH</word>
		<word>CHAR_LENGTH</word>
		<word>CHARACTER_LENGTH</word>
		<word>CONVERT</word>
		<word>LOWER</word>
		<word>OCTET_LENGTH</word>
		<word>OVERLAY</word>
		<word>POSITION</word>
		<word>SUBSTRING</word>
		<word>TRIM</word>
		<word>UPPER</word>
		<!-- Other string functions-->
		<word>ASCII</word>
		<word>BTRIM</word>
		<word>CHR</word>
		<word>CONVERT</word>
		<word>DECODE</word>
		<word>ENCODE</word>
		<word>INITCAP</word>
		<word>LENGTH</word>
		<word>LPAD</word>
		<word>LTRIM</word>
		<word>MD5</word>
		<word>PG_CLIENT_ENCODING</word>
		<word>QUOTE_INDENT</word>
		<word>QUOTE_LITERAL</word>
		<word>REGEXP_REPLACE</word>
		<word>REPEAT</word>
		<word>REPLACE</word>
		<word>RPAD</word>
		<word>RTRIM</word>
		<word>SPLIT_PART</word>
		<word>STRPOS</word>
		<word>SUBSTR</word>
		<word>TO_ASCII</word>
		<word>TO_HEX</word>
		<word>TRANSLATE</word>
		<!-- Datatype conversion function-->
		<word>TO_CHAR</word>
		<word>TO_DATE</word>
		<word>TO_NUMBER</word>
		<word>TO_TIMESTAMP</word>

		<!-- Date/time functions-->
		<word>NOW</word>

		<!-- Aggregate functions -->
		<word>AVG</word>
		<word>COUNT</word>
		<word>MAX</word>
		<word>MIN</word>
		<word>SUM</word>
	</functions>
	
	<datatypes>
		<word>BIGINT</word>
		<word>BIT</word>
		<word>BOOL</word>
		<word>BOOLEAN</word>
		<word>CHAR</word>
		<word>CHARACTER</word>
		<word>DATE</word>
		<word>DECIMAL</word>
		<word>FLOAT</word>
		<word>INT</word>
		<word>INTEGER</word>
		<word>INTERVAL</word>
		<word>NUMERIC</word>
		<word>REAL</word>
		<word>SMALLINT</word>
		<word>TEXT</word>
		<word>TIME</word>
		<word>TIMETZ</word>
		<word>TIMESTAMP</word>
		<word>TIMESTAMPTZ</word>
		<word>VARCHAR</word>
	</datatypes>
</syntax>

